{
  "id": "ban",
  "language": "ban",
  "name": "Balinese",
  "alt_name": "Bali, basa",
  "old_testament": null,
  "new_testament": null,
  "old_testament_abbreviation": null,
  "new_testament_abbreviation": null,
  "books": [
    {
      "id": "01",
      "usfx_code": "GEN",
      "name": "PURWAKANING DADI",
      "abbreviation": "Pur"
    },
    {
      "id": "02",
      "usfx_code": "EXO",
      "name": "PARARUDAN",
      "abbreviation": "Par"
    },
    {
      "id": "03",
      "usfx_code": "LEV",
      "name": "UPACARA",
      "abbreviation": "Up"
    },
    {
      "id": "04",
      "usfx_code": "NUM",
      "name": "CACAH JIWA",
      "abbreviation": "Ca"
    },
    {
      "id": "05",
      "usfx_code": "DEU",
      "name": "PANGELING-ELING",
      "abbreviation": "Pang"
    },
    {
      "id": "06",
      "usfx_code": "JOS",
      "name": "YOSUA",
      "abbreviation": "Yos"
    },
    {
      "id": "07",
      "usfx_code": "JDG",
      "name": "PARAHAKIM",
      "abbreviation": "Parahak"
    },
    {
      "id": "08",
      "usfx_code": "RUT",
      "name": "RUT",
      "abbreviation": "Rut"
    },
    {
      "id": "09",
      "usfx_code": "1SA",
      "name": "1 SAMUEL",
      "abbreviation": "1Sam"
    },
    {
      "id": "10",
      "usfx_code": "2SA",
      "name": "2 SAMUEL",
      "abbreviation": "2Sam"
    },
    {
      "id": "11",
      "usfx_code": "1KI",
      "name": "1 PARARATU",
      "abbreviation": "1Pararat"
    },
    {
      "id": "12",
      "usfx_code": "2KI",
      "name": "2 PARARATU",
      "abbreviation": "2Pararat"
    },
    {
      "id": "13",
      "usfx_code": "1CH",
      "name": "1 BABAD",
      "abbreviation": "1Bab"
    },
    {
      "id": "14",
      "usfx_code": "2CH",
      "name": "2 BABAD",
      "abbreviation": "2Bab"
    },
    {
      "id": "15",
      "usfx_code": "EZR",
      "name": "ESRA",
      "abbreviation": "Es"
    },
    {
      "id": "16",
      "usfx_code": "NEH",
      "name": "NEHEMIA",
      "abbreviation": "Ne"
    },
    {
      "id": "17",
      "usfx_code": "EST",
      "name": "ESTER",
      "abbreviation": "Est"
    },
    {
      "id": "18",
      "usfx_code": "JOB",
      "name": "AYUB",
      "abbreviation": "Ay"
    },
    {
      "id": "19",
      "usfx_code": "PSA",
      "name": "KIDUNG",
      "abbreviation": "Kid"
    },
    {
      "id": "20",
      "usfx_code": "PRO",
      "name": "PITUTUR",
      "abbreviation": "Pit"
    },
    {
      "id": "21",
      "usfx_code": "ECC",
      "name": "GURU PANGAJIAN",
      "abbreviation": "Guru"
    },
    {
      "id": "22",
      "usfx_code": "SNG",
      "name": "KIDUNG GEGURITAN",
      "abbreviation": "Geg"
    },
    {
      "id": "23",
      "usfx_code": "ISA",
      "name": "NABI YESAYA",
      "abbreviation": "Yes"
    },
    {
      "id": "24",
      "usfx_code": "JER",
      "name": "NABI YEREMIA",
      "abbreviation": "Yer"
    },
    {
      "id": "25",
      "usfx_code": "LAM",
      "name": "SESAMBATAN",
      "abbreviation": "Ses"
    },
    {
      "id": "26",
      "usfx_code": "EZK",
      "name": "NABI YEHESKIEL",
      "abbreviation": "Yeh"
    },
    {
      "id": "27",
      "usfx_code": "DAN",
      "name": "NABI DANIEL",
      "abbreviation": "Dan"
    },
    {
      "id": "28",
      "usfx_code": "HOS",
      "name": "NABI HOSEA",
      "abbreviation": "Hos"
    },
    {
      "id": "29",
      "usfx_code": "JOL",
      "name": "NABI YOEL",
      "abbreviation": "Yo"
    },
    {
      "id": "30",
      "usfx_code": "AMO",
      "name": "NABI AMOS",
      "abbreviation": "Am"
    },
    {
      "id": "31",
      "usfx_code": "OBA",
      "name": "NABI OBAJA",
      "abbreviation": "Ob"
    },
    {
      "id": "32",
      "usfx_code": "JON",
      "name": "NABI YUNUS",
      "abbreviation": "Yu"
    },
    {
      "id": "33",
      "usfx_code": "MIC",
      "name": "NABI MIKA",
      "abbreviation": "Mi"
    },
    {
      "id": "34",
      "usfx_code": "NAM",
      "name": "NABI NAHUM",
      "abbreviation": "Na"
    },
    {
      "id": "35",
      "usfx_code": "HAB",
      "name": "NABI HABAKUK",
      "abbreviation": "Ha"
    },
    {
      "id": "36",
      "usfx_code": "ZEP",
      "name": "NABI SEPANYA",
      "abbreviation": "Se"
    },
    {
      "id": "37",
      "usfx_code": "HAG",
      "name": "NABI HAGAI",
      "abbreviation": "Hag"
    },
    {
      "id": "38",
      "usfx_code": "ZEC",
      "name": "NABI SAKARIA",
      "abbreviation": "Sa"
    },
    {
      "id": "39",
      "usfx_code": "MAL",
      "name": "NABI MALEAKI",
      "abbreviation": "Mal"
    },
    {
      "id": "40",
      "usfx_code": "MAT",
      "name": "MATIUS",
      "abbreviation": "Mat"
    },
    {
      "id": "41",
      "usfx_code": "MRK",
      "name": "MARKUS",
      "abbreviation": "Mar"
    },
    {
      "id": "42",
      "usfx_code": "LUK",
      "name": "LUKAS",
      "abbreviation": "Luk"
    },
    {
      "id": "43",
      "usfx_code": "JHN",
      "name": "YOHANES",
      "abbreviation": "Yoh"
    },
    {
      "id": "44",
      "usfx_code": "ACT",
      "name": "PAMARGIN PARAUTUSAN",
      "abbreviation": "Paraut"
    },
    {
      "id": "45",
      "usfx_code": "ROM",
      "name": "ROMA",
      "abbreviation": "Rom"
    },
    {
      "id": "46",
      "usfx_code": "1CO",
      "name": "1 KORINTUS",
      "abbreviation": "1Kor"
    },
    {
      "id": "47",
      "usfx_code": "2CO",
      "name": "2 KORINTUS",
      "abbreviation": "2Kor"
    },
    {
      "id": "48",
      "usfx_code": "GAL",
      "name": "GALATIA",
      "abbreviation": "Gal"
    },
    {
      "id": "49",
      "usfx_code": "EPH",
      "name": "EPESUS",
      "abbreviation": "Ep"
    },
    {
      "id": "50",
      "usfx_code": "PHP",
      "name": "PILIPI",
      "abbreviation": "Pil"
    },
    {
      "id": "51",
      "usfx_code": "COL",
      "name": "KOLOSE",
      "abbreviation": "Kol"
    },
    {
      "id": "52",
      "usfx_code": "1TH",
      "name": "1 TESALONIKA",
      "abbreviation": "1Tes"
    },
    {
      "id": "53",
      "usfx_code": "2TH",
      "name": "2 TESALONIKA",
      "abbreviation": "2Tes"
    },
    {
      "id": "54",
      "usfx_code": "1TI",
      "name": "1 TIMOTIUS",
      "abbreviation": "1Tim"
    },
    {
      "id": "55",
      "usfx_code": "2TI",
      "name": "2 TIMOTIUS",
      "abbreviation": "2Tim"
    },
    {
      "id": "56",
      "usfx_code": "TIT",
      "name": "TITUS",
      "abbreviation": "Tit"
    },
    {
      "id": "57",
      "usfx_code": "PHM",
      "name": "PILEMON",
      "abbreviation": "Pile"
    },
    {
      "id": "58",
      "usfx_code": "HEB",
      "name": "IBRANI",
      "abbreviation": "Ib"
    },
    {
      "id": "59",
      "usfx_code": "JAS",
      "name": "YAKOBUS",
      "abbreviation": "Yak"
    },
    {
      "id": "60",
      "usfx_code": "1PE",
      "name": "1 PETRUS",
      "abbreviation": "1Pet"
    },
    {
      "id": "61",
      "usfx_code": "2PE",
      "name": "2 PETRUS",
      "abbreviation": "2Pet"
    },
    {
      "id": "62",
      "usfx_code": "1JN",
      "name": "1 YOHANES",
      "abbreviation": "1Yoh"
    },
    {
      "id": "63",
      "usfx_code": "2JN",
      "name": "2 YOHANES",
      "abbreviation": "2Yoh"
    },
    {
      "id": "64",
      "usfx_code": "3JN",
      "name": "3 YOHANES",
      "abbreviation": "3Yoh"
    },
    {
      "id": "65",
      "usfx_code": "JUD",
      "name": "YUDAS",
      "abbreviation": "Yud"
    },
    {
      "id": "66",
      "usfx_code": "REV",
      "name": "WAHYU",
      "abbreviation": "Wah"
    }
  ]
}