{
  "id": "ce",
  "language": "ce",
  "name": "Chechen",
  "alt_name": "Нохчийн мотт",
  "old_testament": null,
  "new_testament": null,
  "old_testament_abbreviation": null,
  "new_testament_abbreviation": null,
  "books": [
    {
      "id": "01",
      "usfx_code": "GEN",
      "name": "Доладалар",
      "abbreviation": "Дол"
    },
    {
      "id": "02",
      "usfx_code": "EXO",
      "name": "Арадаккхар",
      "abbreviation": "Ара"
    },
    {
      "id": "03",
      "usfx_code": "LEV",
      "name": "Ӏамалъяр",
      "abbreviation": "Ӏам"
    },
    {
      "id": "04",
      "usfx_code": "NUM",
      "name": "Лелар",
      "abbreviation": "Лел"
    },
    {
      "id": "05",
      "usfx_code": "DEU",
      "name": "Карлабаьккхинарг",
      "abbreviation": "Кар"
    },
    {
      "id": "06",
      "usfx_code": "JOS",
      "name": "ЮшаӀ",
      "abbreviation": "Юш"
    },
    {
      "id": "07",
      "usfx_code": "JDG",
      "name": "Куьйгалхой",
      "abbreviation": "Куьйг"
    },
    {
      "id": "08",
      "usfx_code": "RUT",
      "name": "Рути",
      "abbreviation": "Рут"
    },
    {
      "id": "09",
      "usfx_code": "1SA",
      "name": "Шамъал",
      "abbreviation": "Шам"
    },
    {
      "id": "10",
      "usfx_code": "2SA",
      "name": "Дауд",
      "abbreviation": "Дад"
    },
    {
      "id": "11",
      "usfx_code": "1KI",
      "name": "Сулим",
      "abbreviation": "Сул"
    },
    {
      "id": "12",
      "usfx_code": "2KI",
      "name": "ТӀаьххьарнаш",
      "abbreviation": "ТӀаьххь"
    },
    {
      "id": "13",
      "usfx_code": "1CH",
      "name": "1 Шерашкахь",
      "abbreviation": "1Ше"
    },
    {
      "id": "14",
      "usfx_code": "2CH",
      "name": "2 Шерашкахь",
      "abbreviation": "2Ше"
    },
    {
      "id": "15",
      "usfx_code": "EZR",
      "name": "Ӏезар",
      "abbreviation": "Ӏезар"
    },
    {
      "id": "16",
      "usfx_code": "NEH",
      "name": "Нахьми-ЯхӀу",
      "abbreviation": "Нахь"
    },
    {
      "id": "17",
      "usfx_code": "EST",
      "name": "Эсират",
      "abbreviation": "Эси"
    },
    {
      "id": "18",
      "usfx_code": "JOB",
      "name": "Аюб",
      "abbreviation": "Аюб"
    },
    {
      "id": "19",
      "usfx_code": "PSA",
      "name": "Забур",
      "abbreviation": "Заб"
    },
    {
      "id": "20",
      "usfx_code": "PRO",
      "name": "Кицанаш",
      "abbreviation": "Киц"
    },
    {
      "id": "21",
      "usfx_code": "ECC",
      "name": "Устаз",
      "abbreviation": "Уст"
    },
    {
      "id": "22",
      "usfx_code": "SNG",
      "name": "Илли",
      "abbreviation": "Илли"
    },
    {
      "id": "23",
      "usfx_code": "ISA",
      "name": "ЕшаӀ-ЯхӀу",
      "abbreviation": "Еш"
    },
    {
      "id": "24",
      "usfx_code": "JER",
      "name": "Ярми-ЯхӀу",
      "abbreviation": "Ярм"
    },
    {
      "id": "25",
      "usfx_code": "LAM",
      "name": "Тийжамаш",
      "abbreviation": "Тийж"
    },
    {
      "id": "26",
      "usfx_code": "EZK",
      "name": "Яхьазкхиал",
      "abbreviation": "Яхь"
    },
    {
      "id": "27",
      "usfx_code": "DAN",
      "name": "Даниал",
      "abbreviation": "Дан"
    },
    {
      "id": "28",
      "usfx_code": "HOS",
      "name": "ХӀушаӀ",
      "abbreviation": "ХӀуш"
    },
    {
      "id": "29",
      "usfx_code": "JOL",
      "name": "Юал",
      "abbreviation": "Юал"
    },
    {
      "id": "30",
      "usfx_code": "AMO",
      "name": "Ӏамос",
      "abbreviation": "Ӏамос"
    },
    {
      "id": "31",
      "usfx_code": "OBA",
      "name": "Ӏабди-ЯхӀу",
      "abbreviation": "Ӏаб"
    },
    {
      "id": "32",
      "usfx_code": "JON",
      "name": "Юнус",
      "abbreviation": "Юн"
    },
    {
      "id": "33",
      "usfx_code": "MIC",
      "name": "Мика-ЯхӀу",
      "abbreviation": "Мик"
    },
    {
      "id": "34",
      "usfx_code": "NAM",
      "name": "Нахьум",
      "abbreviation": "Нахьум"
    },
    {
      "id": "35",
      "usfx_code": "HAB",
      "name": "Хьабукъа",
      "abbreviation": "Хьаб"
    },
    {
      "id": "36",
      "usfx_code": "ZEP",
      "name": "Цапни-ЯхӀу",
      "abbreviation": "Цап"
    },
    {
      "id": "37",
      "usfx_code": "HAG",
      "name": "Хьагай",
      "abbreviation": "Хьаг"
    },
    {
      "id": "38",
      "usfx_code": "ZEC",
      "name": "Закри-ЯхӀу",
      "abbreviation": "Зак"
    },
    {
      "id": "39",
      "usfx_code": "MAL",
      "name": "Малъаки",
      "abbreviation": "Мал"
    },
    {
      "id": "40",
      "usfx_code": "MAT",
      "name": "Маттай",
      "abbreviation": "Мат"
    },
    {
      "id": "41",
      "usfx_code": "MRK",
      "name": "Марк",
      "abbreviation": "Мрк"
    },
    {
      "id": "42",
      "usfx_code": "LUK",
      "name": "Лака",
      "abbreviation": "Лак"
    },
    {
      "id": "43",
      "usfx_code": "JHN",
      "name": "Яхьъя",
      "abbreviation": "Яй"
    },
    {
      "id": "44",
      "usfx_code": "ACT",
      "name": "Векалийн",
      "abbreviation": "Век"
    },
    {
      "id": "45",
      "usfx_code": "ROM",
      "name": "Римхошка",
      "abbreviation": "Рим"
    },
    {
      "id": "46",
      "usfx_code": "1CO",
      "name": "1 Коринтхошка",
      "abbreviation": "1Ко"
    },
    {
      "id": "47",
      "usfx_code": "2CO",
      "name": "2 Коринтхошка",
      "abbreviation": "2Ко"
    },
    {
      "id": "48",
      "usfx_code": "GAL",
      "name": "Галатахошка",
      "abbreviation": "Гал"
    },
    {
      "id": "49",
      "usfx_code": "EPH",
      "name": "Эпасхошка",
      "abbreviation": "Эпа"
    },
    {
      "id": "50",
      "usfx_code": "PHP",
      "name": "Пилапхошка",
      "abbreviation": "Пил"
    },
    {
      "id": "51",
      "usfx_code": "COL",
      "name": "Ковлусихошка",
      "abbreviation": "Ков"
    },
    {
      "id": "52",
      "usfx_code": "1TH",
      "name": "1 Тассалникахошка",
      "abbreviation": "1Та"
    },
    {
      "id": "53",
      "usfx_code": "2TH",
      "name": "2 Тассалникахошка",
      "abbreviation": "2Та"
    },
    {
      "id": "54",
      "usfx_code": "1TI",
      "name": "1 Тимапига",
      "abbreviation": "1Ти"
    },
    {
      "id": "55",
      "usfx_code": "2TI",
      "name": "2 Тимапига",
      "abbreviation": "2Ти"
    },
    {
      "id": "56",
      "usfx_code": "TIT",
      "name": "Тите",
      "abbreviation": "Тит"
    },
    {
      "id": "57",
      "usfx_code": "PHM",
      "name": "Пхьалмане",
      "abbreviation": "Пхьал"
    },
    {
      "id": "58",
      "usfx_code": "HEB",
      "name": "Ӏебархошка",
      "abbreviation": "Ӏеб"
    },
    {
      "id": "59",
      "usfx_code": "JAS",
      "name": "Якъуба",
      "abbreviation": "Якъ"
    },
    {
      "id": "60",
      "usfx_code": "1PE",
      "name": "1 Кипин",
      "abbreviation": "1Ки"
    },
    {
      "id": "61",
      "usfx_code": "2PE",
      "name": "2 Кипин",
      "abbreviation": "2Ки"
    },
    {
      "id": "62",
      "usfx_code": "1JN",
      "name": "1 Яхьъяс",
      "abbreviation": "1Я"
    },
    {
      "id": "63",
      "usfx_code": "2JN",
      "name": "2 Яхьъяс",
      "abbreviation": "2Я"
    },
    {
      "id": "64",
      "usfx_code": "3JN",
      "name": "3 Яхьъяс",
      "abbreviation": "3Я"
    },
    {
      "id": "65",
      "usfx_code": "JUD",
      "name": "ЯхӀуда",
      "abbreviation": "ЯхӀ"
    },
    {
      "id": "66",
      "usfx_code": "REV",
      "name": "Довзийтинарг",
      "abbreviation": "Довз"
    }
  ]
}